nonebot_plugin_liteperm/__init__.py
nonebot_plugin_liteperm/command_manager.py
nonebot_plugin_liteperm/config.py
nonebot_plugin_liteperm/nodelib.py
nonebot_plugin_liteperm/on_init.py
nonebot_plugin_liteperm/utils.py
nonebot_plugin_liteperm/API/admin.py
nonebot_plugin_liteperm/API/config.py
nonebot_plugin_liteperm/API/node.py
nonebot_plugin_liteperm/API/rules.py
nonebot_plugin_liteperm/commands/cmd_utils.py
nonebot_plugin_liteperm/commands/lp_chat_group.py
nonebot_plugin_liteperm/commands/lp_perm_group.py
nonebot_plugin_liteperm/commands/lp_user.py
nonebot_plugin_liteperm/commands/main.py
nonebot_plugin_liteperm-0.1.1.dist-info/licenses/LICENSE
nonebot_plugin_liteperm-0.1.1.dist-info/METADATA
nonebot_plugin_liteperm-0.1.1.dist-info/WHEEL
nonebot_plugin_liteperm-0.1.1.dist-info/top_level.txt
nonebot_plugin_liteperm-0.1.1.dist-info/RECORD
