Metadata-Version: 2.4
Name: nonebot_plugin_liteperm
Version: 0.1.1
Summary: 基于权限节点/权限组/特殊权限的Nonebot权限管理插件。
Author-email: JohnRichard4096 <windowserror@163.com>, MrlingXD <wlingzhenyu@163.com>
License: GPL-3.0-or-later
Project-URL: Homepage, https://github.com/LiteSuggarDEV/plugin-liteperm
Project-URL: Source, https://github.com/LiteSuggarDEV/plugin-liteperm
Project-URL: Issue Tracker, https://github.com/LiteSuggarDEV/plugin-liteperm/issues
Keywords: nonebot
Requires-Python: <3.14,>=3.10
License-File: LICENSE
Requires-Dist: nonebot2>=2.2.0
Requires-Dist: nonebot-adapter-onebot>=2.0.0
Requires-Dist: nonebot-plugin-localstore>=0.7
Requires-Dist: typing-extensions>=4.13.2
Requires-Dist: tomli>=2.2.1
Requires-Dist: tomli-w>=1.2.0
Requires-Dist: pydantic>=2.0.0
Dynamic: license-file
